a7/__init__.py
a7/_version.py
a7/auth.py
a7/client.py
a7/config.py
a7/errors.py
a7/resources/__init__.py
a7/resources/algo.py
a7/resources/auction.py
a7/resources/dataset.py
a7/resources/eobi.py
a7/resources/insights.py
a7/resources/mdp.py
a7/resources/orderbook.py
a7/resources/precalc.py
a7/resources/rdi.py
a7/resources/sd.py
a7-0.2.3.dist-info/METADATA
a7-0.2.3.dist-info/WHEEL
a7-0.2.3.dist-info/RECORD
