Metadata-Version: 2.4
Name: a7
Version: 0.2.3
Summary: A simple, synchronous Python SDK for the A7 Analytics Platform by Deutsche Börse
Project-URL: Homepage, https://github.com/Deutsche-Boerse/a7
Project-URL: Documentation, https://github.com/Deutsche-Boerse/a7/blob/master/sdk/README.md
Project-URL: Repository, https://github.com/Deutsche-Boerse/a7
Project-URL: Issues, https://github.com/Deutsche-Boerse/a7/issues
Author-email: Deutsche Börse <support@deutsche-boerse.com>
License: MIT
Keywords: a7,analytics,deutsche-boerse,eurex,finance,market-data,trading,xetra
Classifier: Development Status :: 3 - Alpha
Classifier: Intended Audience :: Developers
Classifier: Intended Audience :: Financial and Insurance Industry
Classifier: License :: OSI Approved :: MIT License
Classifier: Operating System :: OS Independent
Classifier: Programming Language :: Python :: 3
Classifier: Programming Language :: Python :: 3.9
Classifier: Programming Language :: Python :: 3.10
Classifier: Programming Language :: Python :: 3.11
Classifier: Programming Language :: Python :: 3.12
Classifier: Topic :: Office/Business :: Financial
Classifier: Topic :: Software Development :: Libraries :: Python Modules
Classifier: Typing :: Typed
Requires-Python: >=3.9
Requires-Dist: httpx>=0.27.0
Requires-Dist: python-dotenv>=1.0.0
Provides-Extra: dev
Requires-Dist: build>=1.2.0; extra == 'dev'
Requires-Dist: pyright>=1.1.380; extra == 'dev'
Requires-Dist: pytest-cov>=5.0.0; extra == 'dev'
Requires-Dist: pytest>=8.0.0; extra == 'dev'
Requires-Dist: respx>=0.21.0; extra == 'dev'
Requires-Dist: ruff>=0.6.0; extra == 'dev'
Requires-Dist: twine>=5.1.0; extra == 'dev'
